cellarr/CellArrDataset.py
cellarr/CellArrDatasetSlice.py
cellarr/__init__.py
cellarr/build/__init__.py
cellarr/build/build_cellarr_steps.py
cellarr/build/build_cellarrdataset.py
cellarr/build/build_options.py
cellarr/build/buildutils_tiledb_array.py
cellarr/build/buildutils_tiledb_frame.py
cellarr/ml/__init__.py
cellarr/ml/autoencoder.py
cellarr/ml/dataloader.py
cellarr/slurm/README.md
cellarr/slurm/__init__.py
cellarr/slurm/final_assembly.py
cellarr/slurm/finalize_matrix.py
cellarr/slurm/process_cell_metadata.py
cellarr/slurm/process_gene_annotation.py
cellarr/slurm/process_matrix.py
cellarr/slurm/process_matrix_all.py
cellarr/slurm/process_sample_metadata.py
cellarr/utils/__init__.py
cellarr/utils/queryutils_tiledb_frame.py
cellarr/utils/utils_anndata.py
cellarr-0.6.1.dist-info/licenses/LICENSE.txt
cellarr-0.6.1.dist-info/METADATA
cellarr-0.6.1.dist-info/WHEEL
cellarr-0.6.1.dist-info/entry_points.txt
cellarr-0.6.1.dist-info/top_level.txt
cellarr-0.6.1.dist-info/RECORD
