Metadata-Version: 2.4
Name: cellarr
Version: 0.6.1
Summary: TileDB-based array storage for genomics data collections.
Home-page: https://github.com/cellarr/cellarr
Author: Jayaram Kancherla
Author-email: jayaram.kancherla@gmail.com
License: MIT
Project-URL: Documentation, https://github.com/cellarr/cellarr
Platform: any
Classifier: Development Status :: 4 - Beta
Classifier: Programming Language :: Python
Requires-Python: >=3.9
License-File: LICENSE.txt
Requires-Dist: importlib-metadata; python_version < "3.8"
Requires-Dist: anndata
Requires-Dist: pandas
Requires-Dist: scipy
Requires-Dist: tiledb
Requires-Dist: pyarrow>=1.0
Requires-Dist: mopsy
Requires-Dist: summarizedexperiment>=0.4.5
Provides-Extra: optional
Requires-Dist: torch; extra == "optional"
Requires-Dist: pytorch-lightning; extra == "optional"
Provides-Extra: testing
Requires-Dist: setuptools; extra == "testing"
Requires-Dist: pytest; extra == "testing"
Requires-Dist: pytest-cov; extra == "testing"
Requires-Dist: torch; extra == "testing"
Requires-Dist: pytorch-lightning; extra == "testing"
Dynamic: license-file
